ecasb2share/__init__.py
ecasb2share/ecasb2shareclient.py
ecasb2share/exceptions.py
ecasb2share/requests.py
ecasb2share/tests/__init__.py
ecasb2share/tests/test_client.py
ecasb2share/utils/__init__.py
ecasb2share/utils/exceptions.py
ecasb2share/utils/loggerhandler.py
ecasb2share-0.0.1b16.dist-info/AUTHORS.rst
ecasb2share-0.0.1b16.dist-info/LICENSE.txt
ecasb2share-0.0.1b16.dist-info/METADATA
ecasb2share-0.0.1b16.dist-info/WHEEL
ecasb2share-0.0.1b16.dist-info/top_level.txt
ecasb2share-0.0.1b16.dist-info/RECORD
