Metadata-Version: 2.1
Name: ecasb2share
Version: 0.0.1b16
Summary: ecasb2share provides a python library to interact with B2SHARE REST API.
Home-page: https://github.com/SofianeB/ECAS-B2SHARE
Author: Sofiane Bendoukha
Author-email: bendoukha@dkrz.de
License: mit
Keywords: ecas rest python eosc-hub b2share
Platform: any
Classifier: Development Status :: 4 - Beta
Classifier: Operating System :: OS Independent
Classifier: Programming Language :: Python :: 3
Classifier: Topic :: Software Development :: Bug Tracking
Requires-Dist: requests (>=1.0)
Requires-Dist: nose
Requires-Dist: Click
Provides-Extra: testing
Requires-Dist: pytest ; extra == 'testing'
Requires-Dist: pytest-cov ; extra == 'testing'
